dicom_echo-0.2.2.dist-info/METADATA
dicom_echo-0.2.2.dist-info/WHEEL
dicom_echo-0.2.2.dist-info/entry_points.txt
dicom_echo-0.2.2.dist-info/licenses/LICENSE.md
dicom_echo/backend.pyi
dicom_echo/cli.md
dicom_echo/cli.py
dicom_echo/py.typed
dicom_echo/__init__.py
dicom_echo/__main__.py
dicom_echo/backend.cp312-win32.pyd
dicom_echo-0.2.2.dist-info/RECORD
