Metadata-Version: 2.3
Name: dicom-echo
Version: 0.2.2
Classifier: Development Status :: 2 - Pre-Alpha
Classifier: Intended Audience :: Developers
Classifier: Intended Audience :: Healthcare Industry
Classifier: Intended Audience :: Science/Research
Classifier: Intended Audience :: System Administrators
Classifier: License :: OSI Approved :: MIT License
Classifier: Operating System :: OS Independent
Classifier: Programming Language :: Python
Classifier: Programming Language :: Python :: 3 :: Only
Classifier: Programming Language :: Python :: 3.8
Classifier: Programming Language :: Python :: 3.9
Classifier: Programming Language :: Python :: 3.10
Classifier: Programming Language :: Python :: 3.11
Classifier: Programming Language :: Python :: 3.12
Classifier: Programming Language :: Python :: 3.13
Classifier: Programming Language :: Rust
Classifier: Topic :: Scientific/Engineering
Classifier: Topic :: Scientific/Engineering :: Medical Science Apps.
Classifier: Topic :: Software Development :: Libraries
Classifier: Topic :: Software Development :: Libraries :: Python Modules
Classifier: Typing :: Typed
Requires-Dist: typer ~=0.12.5
Requires-Dist: typing-extensions ~=4.12.2 ; python_version < '3.9'
License-File: LICENSE.md
Summary: A lightweight, cross-platform, blazingly fast implementation of the C-ECHO DICOM procedure. 🔥
Author-email: Bryant Finney <bryant.finney@outlook.com>
Requires-Python: >=3.8.1, <4
Project-URL: changelog, https://github.com/rusty-dicom/dicom-echo/releases
Project-URL: documentation, https://rusty-dicom.github.io/dicom-echo/dicom_echo.html
Project-URL: homepage, https://github.com/rusty-dicom/dicom-echo
Project-URL: issues, https://github.com/rusty-dicom/dicom-echo/issues
Project-URL: readthedocs, https://dicom-echo.readthedocs.io/home.html
Project-URL: source, https://github.com/rusty-dicom/dicom-echo
